README.md
setup.py
pyranges_db/__init__.py
pyranges_db/ensembl.py
pyranges_db/gencode.py
pyranges_db/gwas_catalog.py
pyranges_db/methods.py
pyranges_db/ucsc.py
pyranges_db/version.py
pyranges_db.egg-info/PKG-INFO
pyranges_db.egg-info/SOURCES.txt
pyranges_db.egg-info/dependency_links.txt
pyranges_db.egg-info/requires.txt
pyranges_db.egg-info/top_level.txt