Metadata-Version: 1.1
Name: pyranges-db
Version: 0.0.7
Summary: Database add-on for PyRanges.
Home-page: http://github.com/pyranges/pyranges_db
Author: Endre Bakken Stovner
Author-email: endrebak85@gmail.com
License: MIT
Keywords: Bioinformatics
Platform: UNKNOWN
Classifier: Programming Language :: Python :: 3
Classifier: Development Status :: 4 - Beta
Classifier: Environment :: Other Environment
Classifier: Intended Audience :: Developers
Classifier: Intended Audience :: Science/Research
Classifier: License :: OSI Approved :: MIT License
Classifier: Operating System :: POSIX :: Linux
Classifier: Operating System :: MacOS :: MacOS X
Classifier: Topic :: Scientific/Engineering
